MANIFEST.in
README.txt
mentteslabs.theme-configure.zcml
setup.py
docs/AUTHORS.txt
docs/HISTORY.txt
docs/INSTALL.txt
docs/LICENSE.GPL
docs/LICENSE.txt
plonetheme/__init__.py
plonetheme.labs.egg-info/PKG-INFO
plonetheme.labs.egg-info/SOURCES.txt
plonetheme.labs.egg-info/dependency_links.txt
plonetheme.labs.egg-info/entry_points.txt
plonetheme.labs.egg-info/namespace_packages.txt
plonetheme.labs.egg-info/not-zip-safe
plonetheme.labs.egg-info/requires.txt
plonetheme.labs.egg-info/top_level.txt
plonetheme/labs/__init__.py
plonetheme/labs/configure.zcml
plonetheme/labs/profiles.zcml
plonetheme/labs/setuphandlers.py
plonetheme/labs/skins.zcml
plonetheme/labs/version.txt
plonetheme/labs/Extensions/Install.py
plonetheme/labs/Extensions/__init__.py
plonetheme/labs/browser/__init__.py
plonetheme/labs/browser/configure.zcml
plonetheme/labs/browser/interfaces.py
plonetheme/labs/browser/viewlet.pt
plonetheme/labs/browser/viewlets.py
plonetheme/labs/browser/images/bg-button-header.png
plonetheme/labs/browser/images/bg-header.png
plonetheme/labs/browser/images/bg-portlet-header.png
plonetheme/labs/browser/images/bgheader.png
plonetheme/labs/browser/stylesheets/README.txt
plonetheme/labs/browser/templates/personal_bar.pt
plonetheme/labs/profiles/default/browserlayer.xml
plonetheme/labs/profiles/default/cssregistry.xml
plonetheme/labs/profiles/default/import_steps.xml
plonetheme/labs/profiles/default/jsregistry.xml
plonetheme/labs/profiles/default/metadata.xml
plonetheme/labs/profiles/default/plonetheme.labs_various.txt
plonetheme/labs/profiles/default/skins.xml
plonetheme/labs/profiles/default/viewlets.xml
plonetheme/labs/profiles/uninstall/cssregistry.xml
plonetheme/labs/profiles/uninstall/skins.xml
plonetheme/labs/profiles/uninstall/viewlets.xml
plonetheme/labs/skins/plonetheme_labs_custom_images/favicon.ico
plonetheme/labs/skins/plonetheme_labs_custom_images/logomentteslabs.jpg
plonetheme/labs/skins/plonetheme_labs_custom_templates/CONTENT.txt
plonetheme/labs/skins/plonetheme_labs_styles/IEFixes.css
plonetheme/labs/skins/plonetheme_labs_styles/base_properties.props
plonetheme/labs/skins/plonetheme_labs_styles/main.css.dtml
plonetheme/labs/skins/plonetheme_labs_styles/s5_pretty.css.dtml
plonetheme/labs/tests/__init__.py
plonetheme/labs/tests/base.py
plonetheme/labs/tests/test_setup.py