Metadata-Version: 1.0
Name: plonetheme.labs
Version: 1.1b1
Summary: An installable theme for Plone
Home-page: http://plone.org/products/plonetheme-labs/
Author: Marcelo Huens, Noelia Chaves
Author-email: info@menttes.com
License: GPL
Keywords: web zope plone theme
Platform: UNKNOWN
Classifier: Framework :: Plone
Classifier: Programming Language :: Python
Classifier: Topic :: Software Development :: Libraries :: Python Modules
